sar_logic/sar_logic.v
module sar_logic (
    input  wire clk,
    input  wire rst,
    input  wire comp_out,
    output reg  b3,
    output reg  b2,
    output reg  b1,
    output reg  b0,
    output reg  eoc
);
    reg [2:0] state;
    always @(posedge clk or posedge rst) begin
        if (rst) begin
            b3<=0; b2<=0; b1<=0; b0<=0; eoc<=0; state<=0;
        end else begin
            case (state)
                3'd0: begin b3<=1; b2<=0; b1<=0; b0<=0; eoc<=0; state<=3'd1; end
                3'd1: begin b3<=comp_out?0:1; b2<=1; state<=3'd2; end
                3'd2: begin b2<=comp_out?0:1; b1<=1; state<=3'd3; end
                3'd3: begin b1<=comp_out?0:1; b0<=1; state<=3'd4; end
                3'd4: begin b0<=comp_out?0:1; eoc<=1; state<=3'd0; end
                default: state<=3'd0;
            endcase
        end
    end
endmodule

sar_logic/sar_logic_tb.v
`timescale 1ns/1ps
module sar_logic_tb;
    reg clk, rst, comp_out;
    wire b3, b2, b1, b0, eoc;

    sar_logic uut(.clk(clk),.rst(rst),.comp_out(comp_out),.b3(b3),.b2(b2),.b1(b1),.b0(b0),.eoc(eoc));

    always #5 clk = ~clk;

    // 毎クロック状態を表示
    always @(posedge clk) begin
        $display("t=%0t state=%0d comp=%b b3=%b b2=%b b1=%b b0=%b eoc=%b",
                 $time, uut.state, comp_out, b3, b2, b1, b0, eoc);
    end

    initial begin
        clk=0; rst=1; comp_out=0;
        #12 rst=0;
        @(posedge clk); #1; comp_out=1;
        @(posedge clk); #1; comp_out=0;
        @(posedge clk); #1; comp_out=1;
        @(posedge clk); #1; comp_out=0;
        @(posedge clk); #1;
        #10 $finish;
    end
endmodule

sar_logic/sar_logic_tb.vcd
$date
	Thu Feb 26 21:33:49 2026
$end
$version
	Icarus Verilog
$end
$timescale
	1ps
$end
$scope module sar_logic_tb $end
$var wire 1 ! eoc $end
$var wire 1 " b3 $end
$var wire 1 # b2 $end
$var wire 1 $ b1 $end
$var wire 1 % b0 $end
$var reg 1 & clk $end
$var reg 1 ' comp_out $end
$var reg 1 ( rst $end
$scope module uut $end
$var wire 1 & clk $end
$var wire 1 ' comp_out $end
$var wire 1 ( rst $end
$var reg 1 % b0 $end
$var reg 1 $ b1 $end
$var reg 1 # b2 $end
$var reg 1 " b3 $end
$var reg 1 ! eoc $end
$var reg 3 ) state [2:0] $end
$upscope $end
$upscope $end
$enddefinitions $end
$comment Show the parameter values. $end
$dumpall
$end
#0
$dumpvars
b0 )
1(
0'
0&
0%
0$
0#
0"
0!
$end
#5000
1&
#10000
0&
#12000
0(
#15000
b1 )
1"
1&
#16000
1'
#20000
0&
#25000
b10 )
1#
0"
1&
#26000
0'
#30000
0&
#35000
b11 )
1$
1&
#36000
1'
#40000
0&
#45000
b100 )
1%
0$
1&
#46000
0'
#50000
0&
#55000
b0 )
1!
1&
#60000
0&
#65000
b1 )
0!
0%
0#
1"
1&
